{
    "wallpaper": "/home/lyneca/Pictures/hobbes/laugh.png",
    "alpha": "100",
    "special": {
        "background": "#18120a",
        "foreground": "#ecece2",
        "cursor": "#ecece2"
    },
    "colors": {
        "color0": "#18120a",
        "color1": "#BBA059",
        "color2": "#D8974E",
        "color3": "#61778D",
        "color4": "#B1B2B0",
        "color5": "#EADBA5",
        "color6": "#D9D4D1",
        "color7": "#ecece2",
        "color8": "#a5a59e",
        "color9": "#BBA059",
        "color10": "#D8974E",
        "color11": "#61778D",
        "color12": "#B1B2B0",
        "color13": "#EADBA5",
        "color14": "#D9D4D1",
        "color15": "#ecece2"
    }
}